{"id": "pbGAy8GzWaI", "title": "\u30a4\u30d6\u30cb\u30f3\u30b0\u3000\u30b7\u30e3\u30ef\u30fc", "formats": [{"asr": 48000, "filesize": 1568016, "format_id": "249", "format_note": "tiny", "fps": null, "height": null, "quality": 0, "tbr": 56.683, "url": "https://rr5---sn-0opoxu-ihv6.googlevideo.com/videoplayback?expire=1670742951&ei=Ry-VY6CUEc3tkgac65tQ&ip=189.173.225.87&id=o-AGW8qPrnFC62l8HBPtUaufyw0B3iomcOkIgdfUnlTkgK&itag=249&source=youtube&requiressl=yes&mh=4D&mm=31%2C29&mn=sn-0opoxu-ihv6%2Csn-q4flrn7r&ms=au%2Crdu&mv=m&mvi=5&pl=24&gcr=mx&initcwndbps=777500&vprv=1&mime=audio%2Fwebm&ns=d-VkRmYy579Rj0Om3oVtrI4J&gir=yes&clen=1568016&dur=221.301&lmt=1573728644688627&mt=1670721185&fvip=3&keepalive=yes&fexp=24001373%2C24007246&c=WEB&txp=1301222&n=KrE8AO5fY6Rg8eyYn&sparams=expire%2Cei%2Cip%2Cid%2Citag%2Csource%2Crequiressl%2Cgcr%2Cvprv%2Cmime%2Cns%2Cgir%2Cclen%2Cdur%2Clmt&lsparams=mh%2Cmm%2Cmn%2Cms%2Cmv%2Cmvi%2Cpl%2Cinitcwndbps&lsig=AG3C_xAwRAIgH1ADE6qE8S0OHJfAsaIepjUuSHt7ix3Mw3uSHOx0RPECIDFDVxjGEBfgui3zIeFP--HNp_wddS0BZ14YQ9DEQPmC&sig=AOq0QJ8wRQIgD2En1IifMiKlKEve8wyYtiPLKzU0kp9Qd0GoO3Ho6ZgCIQD3PZ-qIeJoMqhme3Zy0ET0XgUASUYClvgV-Qdf07gHIA==", "width": null, "ext": "webm", "vcodec": "none", "acodec": "opus", "abr": 56.683, "downloader_options": {"http_chunk_size": 10485760}, "container": "webm_dash", "format": "249 - audio only (tiny)", "protocol": "https", "http_headers": {"User-Agent": "Mozilla/5.0 (Windows NT 10.0; Win64; x64) AppleWebKit/537.36 (KHTML, like Gecko) Chrome/72.0.3626.88 Safari/537.36", "Accept-Charset": "ISO-8859-1,utf-8;q=0.7,*;q=0.7", "Accept": "text/html,application/xhtml+xml,application/xml;q=0.9,*/*;q=0.8", "Accept-Encoding": "gzip, deflate", "Accept-Language": "en-us,en;q=0.5"}}, {"asr": 48000, "filesize": 2038672, "format_id": "250", "format_note": "tiny", "fps": null, "height": null, "quality": 0, "tbr": 73.697, "url": "https://rr5---sn-0opoxu-ihv6.googlevideo.com/videoplayback?expire=1670742951&ei=Ry-VY6CUEc3tkgac65tQ&ip=189.173.225.87&id=o-AGW8qPrnFC62l8HBPtUaufyw0B3iomcOkIgdfUnlTkgK&itag=250&source=youtube&requiressl=yes&mh=4D&mm=31%2C29&mn=sn-0opoxu-ihv6%2Csn-q4flrn7r&ms=au%2Crdu&mv=m&mvi=5&pl=24&gcr=mx&initcwndbps=777500&vprv=1&mime=audio%2Fwebm&ns=d-VkRmYy579Rj0Om3oVtrI4J&gir=yes&clen=2038672&dur=221.301&lmt=1573728647884707&mt=1670721185&fvip=3&keepalive=yes&fexp=24001373%2C24007246&c=WEB&txp=1301222&n=KrE8AO5fY6Rg8eyYn&sparams=expire%2Cei%2Cip%2Cid%2Citag%2Csource%2Crequiressl%2Cgcr%2Cvprv%2Cmime%2Cns%2Cgir%2Cclen%2Cdur%2Clmt&lsparams=mh%2Cmm%2Cmn%2Cms%2Cmv%2Cmvi%2Cpl%2Cinitcwndbps&lsig=AG3C_xAwRgIhAOjr_YJjTB3NBpJhCUTXs4YGEaBDAJfmcpLzk_XJeKVNAiEAqU4aYHwqWfItreZKiaxsgL3tC6mF2DYHFuRpPamzZdE%3D&sig=AOq0QJ8wRQIgHVPgdosMteG19ATQYkhOKAD3nH6NFfz28og_LjRRSbACIQC6forUSVnPiQ4Bk-3wlbM4S0Znu7Y1QHjhauW8HEjZPg==", "width": null, "ext": "webm", "vcodec": "none", "acodec": "opus", "abr": 73.697, "downloader_options": {"http_chunk_size": 10485760}, "container": "webm_dash", "format": "250 - audio only (tiny)", "protocol": "https", "http_headers": {"User-Agent": "Mozilla/5.0 (Windows NT 10.0; Win64; x64) AppleWebKit/537.36 (KHTML, like Gecko) Chrome/72.0.3626.88 Safari/537.36", "Accept-Charset": "ISO-8859-1,utf-8;q=0.7,*;q=0.7", "Accept": "text/html,application/xhtml+xml,application/xml;q=0.9,*/*;q=0.8", "Accept-Encoding": "gzip, deflate", "Accept-Language": "en-us,en;q=0.5"}}, {"asr": 44100, "filesize": 3583101, "format_id": "140", "format_note": "tiny", "fps": null, "height": null, "quality": 0, "tbr": 129.534, "url": "https://rr5---sn-0opoxu-ihv6.googlevideo.com/videoplayback?expire=1670742951&ei=Ry-VY6CUEc3tkgac65tQ&ip=189.173.225.87&id=o-AGW8qPrnFC62l8HBPtUaufyw0B3iomcOkIgdfUnlTkgK&itag=140&source=youtube&requiressl=yes&mh=4D&mm=31%2C29&mn=sn-0opoxu-ihv6%2Csn-q4flrn7r&ms=au%2Crdu&mv=m&mvi=5&pl=24&gcr=mx&initcwndbps=777500&vprv=1&mime=audio%2Fmp4&ns=d-VkRmYy579Rj0Om3oVtrI4J&gir=yes&clen=3583101&dur=221.291&lmt=1573727840595260&mt=1670721185&fvip=3&keepalive=yes&fexp=24001373%2C24007246&c=WEB&txp=1311222&n=KrE8AO5fY6Rg8eyYn&sparams=expire%2Cei%2Cip%2Cid%2Citag%2Csource%2Crequiressl%2Cgcr%2Cvprv%2Cmime%2Cns%2Cgir%2Cclen%2Cdur%2Clmt&lsparams=mh%2Cmm%2Cmn%2Cms%2Cmv%2Cmvi%2Cpl%2Cinitcwndbps&lsig=AG3C_xAwRQIgdvVTLY2kMfao9ygp1pOiBQHqqoqM9JMxwQseg-gOaOECIQDONikZfNkT04Zvvf4ST8cjVLXHLV5On7h02NlBabF_CQ%3D%3D&sig=AOq0QJ8wRQIhAJRp6LkMgK4okUY_f2IVPBb79Bnjin2iRfGvhHNu9aiIAiBzA16kju38i7nu5zY5bdVOXJatc__nezcFoCP2hYUDIg==", "width": null, "ext": "m4a", "vcodec": "none", "acodec": "mp4a.40.2", "abr": 129.534, "downloader_options": {"http_chunk_size": 10485760}, "container": "m4a_dash", "format": "140 - audio only (tiny)", "protocol": "https", "http_headers": {"User-Agent": "Mozilla/5.0 (Windows NT 10.0; Win64; x64) AppleWebKit/537.36 (KHTML, like Gecko) Chrome/72.0.3626.88 Safari/537.36", "Accept-Charset": "ISO-8859-1,utf-8;q=0.7,*;q=0.7", "Accept": "text/html,application/xhtml+xml,application/xml;q=0.9,*/*;q=0.8", "Accept-Encoding": "gzip, deflate", "Accept-Language": "en-us,en;q=0.5"}}, {"asr": 48000, "filesize": 3923568, "format_id": "251", "format_note": "tiny", "fps": null, "height": null, "quality": 0, "tbr": 141.836, "url": "https://rr5---sn-0opoxu-ihv6.googlevideo.com/videoplayback?expire=1670742951&ei=Ry-VY6CUEc3tkgac65tQ&ip=189.173.225.87&id=o-AGW8qPrnFC62l8HBPtUaufyw0B3iomcOkIgdfUnlTkgK&itag=251&source=youtube&requiressl=yes&mh=4D&mm=31%2C29&mn=sn-0opoxu-ihv6%2Csn-q4flrn7r&ms=au%2Crdu&mv=m&mvi=5&pl=24&gcr=mx&initcwndbps=777500&vprv=1&mime=audio%2Fwebm&ns=d-VkRmYy579Rj0Om3oVtrI4J&gir=yes&clen=3923568&dur=221.301&lmt=1573728649589827&mt=1670721185&fvip=3&keepalive=yes&fexp=24001373%2C24007246&c=WEB&txp=1301222&n=KrE8AO5fY6Rg8eyYn&sparams=expire%2Cei%2Cip%2Cid%2Citag%2Csource%2Crequiressl%2Cgcr%2Cvprv%2Cmime%2Cns%2Cgir%2Cclen%2Cdur%2Clmt&lsparams=mh%2Cmm%2Cmn%2Cms%2Cmv%2Cmvi%2Cpl%2Cinitcwndbps&lsig=AG3C_xAwRQIhAPLPrGwpxWDLxQbSv_21snbcJw9fibiEFygCsEUDEOyGAiBzgvcZIl31Uz3pzMvP49zhjUZ2g41HFUTkUwuSdTlWBQ%3D%3D&sig=AOq0QJ8wRAIgXP9xUdYhr4v0n620nQ2hTXfh4rZM1zq0kTArqCy_IG0CIFXtTDypjq5upUi8H84OOXV-zM0WST5YNc5RTpswPVTj", "width": null, "ext": "webm", "vcodec": "none", "acodec": "opus", "abr": 141.836, "downloader_options": {"http_chunk_size": 10485760}, "container": "webm_dash", "format": "251 - audio only (tiny)", "protocol": "https", "http_headers": {"User-Agent": "Mozilla/5.0 (Windows NT 10.0; Win64; x64) AppleWebKit/537.36 (KHTML, like Gecko) Chrome/72.0.3626.88 Safari/537.36", "Accept-Charset": "ISO-8859-1,utf-8;q=0.7,*;q=0.7", "Accept": "text/html,application/xhtml+xml,application/xml;q=0.9,*/*;q=0.8", "Accept-Encoding": "gzip, deflate", "Accept-Language": "en-us,en;q=0.5"}}, {"asr": null, "filesize": 614035, "format_id": "278", "format_note": "144p", "fps": 25, "height": 144, "quality": 0, "tbr": 22.199, "url": "https://rr5---sn-0opoxu-ihv6.googlevideo.com/videoplayback?expire=1670742951&ei=Ry-VY6CUEc3tkgac65tQ&ip=189.173.225.87&id=o-AGW8qPrnFC62l8HBPtUaufyw0B3iomcOkIgdfUnlTkgK&itag=278&aitags=133%2C134%2C135%2C136%2C137%2C160%2C242%2C243%2C244%2C247%2C248%2C278&source=youtube&requiressl=yes&mh=4D&mm=31%2C29&mn=sn-0opoxu-ihv6%2Csn-q4flrn7r&ms=au%2Crdu&mv=m&mvi=5&pl=24&gcr=mx&initcwndbps=777500&vprv=1&mime=video%2Fwebm&ns=d-VkRmYy579Rj0Om3oVtrI4J&gir=yes&clen=614035&dur=221.280&lmt=1573728913984350&mt=1670721185&fvip=3&keepalive=yes&fexp=24001373%2C24007246&c=WEB&txp=1301222&n=KrE8AO5fY6Rg8eyYn&sparams=expire%2Cei%2Cip%2Cid%2Caitags%2Csource%2Crequiressl%2Cgcr%2Cvprv%2Cmime%2Cns%2Cgir%2Cclen%2Cdur%2Clmt&lsparams=mh%2Cmm%2Cmn%2Cms%2Cmv%2Cmvi%2Cpl%2Cinitcwndbps&lsig=AG3C_xAwRQIgRj6o8Wz9jah5AAjy7a4Ot-xVQXFsSNUwdXxvJngoh84CIQDyzF-UxMzVJoIJ_xtbAdzHrRVBlz3zA1ylrGC-0u6YNA%3D%3D&sig=AOq0QJ8wRgIhAOAk2ExTyVx_91tgDlTHM_kCleEEdlY-UptS4WKzt6AUAiEAyhZMg6egIup4I6OCAWRapnP9ohO5UyaftycxkdhOPB0=", "width": 144, "ext": "webm", "vcodec": "vp9", "acodec": "none", "vbr": 22.199, "downloader_options": {"http_chunk_size": 10485760}, "container": "webm_dash", "format": "278 - 144x144 (144p)", "protocol": "https", "http_headers": {"User-Agent": "Mozilla/5.0 (Windows NT 10.0; Win64; x64) AppleWebKit/537.36 (KHTML, like Gecko) Chrome/72.0.3626.88 Safari/537.36", "Accept-Charset": "ISO-8859-1,utf-8;q=0.7,*;q=0.7", "Accept": "text/html,application/xhtml+xml,application/xml;q=0.9,*/*;q=0.8", "Accept-Encoding": "gzip, deflate", "Accept-Language": "en-us,en;q=0.5"}}, {"asr": null, "filesize": 820538, "format_id": "160", "format_note": "144p", "fps": 25, "height": 144, "quality": 0, "tbr": 29.665, "url": "https://rr5---sn-0opoxu-ihv6.googlevideo.com/videoplayback?expire=1670742951&ei=Ry-VY6CUEc3tkgac65tQ&ip=189.173.225.87&id=o-AGW8qPrnFC62l8HBPtUaufyw0B3iomcOkIgdfUnlTkgK&itag=160&aitags=133%2C134%2C135%2C136%2C137%2C160%2C242%2C243%2C244%2C247%2C248%2C278&source=youtube&requiressl=yes&mh=4D&mm=31%2C29&mn=sn-0opoxu-ihv6%2Csn-q4flrn7r&ms=au%2Crdu&mv=m&mvi=5&pl=24&gcr=mx&initcwndbps=777500&vprv=1&mime=video%2Fmp4&ns=d-VkRmYy579Rj0Om3oVtrI4J&gir=yes&clen=820538&dur=221.280&lmt=1573727865926150&mt=1670721185&fvip=3&keepalive=yes&fexp=24001373%2C24007246&c=WEB&txp=1311222&n=KrE8AO5fY6Rg8eyYn&sparams=expire%2Cei%2Cip%2Cid%2Caitags%2Csource%2Crequiressl%2Cgcr%2Cvprv%2Cmime%2Cns%2Cgir%2Cclen%2Cdur%2Clmt&lsparams=mh%2Cmm%2Cmn%2Cms%2Cmv%2Cmvi%2Cpl%2Cinitcwndbps&lsig=AG3C_xAwRQIhALRT_vcQYEMXq--CdATrCLMNMxWBK79gH2yMd-C0Y3zEAiBoRfYYnuWvSPhhrrmoGZNy2srb8PUSzvlK8JXYu7QR-g%3D%3D&sig=AOq0QJ8wRAIgHmdCfrKcLSaph5AR-6pbK4LOzPfCtdMwL1nzsw0UfHUCIFySyT5JKWQ0WQjHN25m-it9jPRq8Ntn4sEog2oCkdA3", "width": 144, "ext": "mp4", "vcodec": "avc1.4d400b", "acodec": "none", "vbr": 29.665, "downloader_options": {"http_chunk_size": 10485760}, "container": "mp4_dash", "format": "160 - 144x144 (144p)", "protocol": "https", "http_headers": {"User-Agent": "Mozilla/5.0 (Windows NT 10.0; Win64; x64) AppleWebKit/537.36 (KHTML, like Gecko) Chrome/72.0.3626.88 Safari/537.36", "Accept-Charset": "ISO-8859-1,utf-8;q=0.7,*;q=0.7", "Accept": "text/html,application/xhtml+xml,application/xml;q=0.9,*/*;q=0.8", "Accept-Encoding": "gzip, deflate", "Accept-Language": "en-us,en;q=0.5"}}, {"asr": null, "filesize": 1213796, "format_id": "242", "format_note": "240p", "fps": 25, "height": 240, "quality": 1, "tbr": 43.882, "url": "https://rr5---sn-0opoxu-ihv6.googlevideo.com/videoplayback?expire=1670742951&ei=Ry-VY6CUEc3tkgac65tQ&ip=189.173.225.87&id=o-AGW8qPrnFC62l8HBPtUaufyw0B3iomcOkIgdfUnlTkgK&itag=242&aitags=133%2C134%2C135%2C136%2C137%2C160%2C242%2C243%2C244%2C247%2C248%2C278&source=youtube&requiressl=yes&mh=4D&mm=31%2C29&mn=sn-0opoxu-ihv6%2Csn-q4flrn7r&ms=au%2Crdu&mv=m&mvi=5&pl=24&gcr=mx&initcwndbps=777500&vprv=1&mime=video%2Fwebm&ns=d-VkRmYy579Rj0Om3oVtrI4J&gir=yes&clen=1213796&dur=221.280&lmt=1573728913971254&mt=1670721185&fvip=3&keepalive=yes&fexp=24001373%2C24007246&c=WEB&txp=1301222&n=KrE8AO5fY6Rg8eyYn&sparams=expire%2Cei%2Cip%2Cid%2Caitags%2Csource%2Crequiressl%2Cgcr%2Cvprv%2Cmime%2Cns%2Cgir%2Cclen%2Cdur%2Clmt&lsparams=mh%2Cmm%2Cmn%2Cms%2Cmv%2Cmvi%2Cpl%2Cinitcwndbps&lsig=AG3C_xAwRAIgOKuFvXLrtwrz7qPz3QHle8_eeK_5SUdFSiRGVIH4FZYCIFGY4ZYA8pwKUA8W5Eosuuwq7jMw-EkkvHj8OH42WVmr&sig=AOq0QJ8wRgIhAKtGaok384nrjY8dBwsgLbsETknxfPO0ljfAcZFWLvAHAiEAksWkr4K3XhCs8ldX9OzmwjwCaGKQFanmj0hhY0_SmaI=", "width": 240, "ext": "webm", "vcodec": "vp9", "acodec": "none", "vbr": 43.882, "downloader_options": {"http_chunk_size": 10485760}, "container": "webm_dash", "format": "242 - 240x240 (240p)", "protocol": "https", "http_headers": {"User-Agent": "Mozilla/5.0 (Windows NT 10.0; Win64; x64) AppleWebKit/537.36 (KHTML, like Gecko) Chrome/72.0.3626.88 Safari/537.36", "Accept-Charset": "ISO-8859-1,utf-8;q=0.7,*;q=0.7", "Accept": "text/html,application/xhtml+xml,application/xml;q=0.9,*/*;q=0.8", "Accept-Encoding": "gzip, deflate", "Accept-Language": "en-us,en;q=0.5"}}, {"asr": null, "filesize": 1864364, "format_id": "133", "format_note": "240p", "fps": 25, "height": 240, "quality": 1, "tbr": 67.402, "url": "https://rr5---sn-0opoxu-ihv6.googlevideo.com/videoplayback?expire=1670742951&ei=Ry-VY6CUEc3tkgac65tQ&ip=189.173.225.87&id=o-AGW8qPrnFC62l8HBPtUaufyw0B3iomcOkIgdfUnlTkgK&itag=133&aitags=133%2C134%2C135%2C136%2C137%2C160%2C242%2C243%2C244%2C247%2C248%2C278&source=youtube&requiressl=yes&mh=4D&mm=31%2C29&mn=sn-0opoxu-ihv6%2Csn-q4flrn7r&ms=au%2Crdu&mv=m&mvi=5&pl=24&gcr=mx&initcwndbps=777500&vprv=1&mime=video%2Fmp4&ns=d-VkRmYy579Rj0Om3oVtrI4J&gir=yes&clen=1864364&dur=221.280&lmt=1573727861123159&mt=1670721185&fvip=3&keepalive=yes&fexp=24001373%2C24007246&c=WEB&txp=1311222&n=KrE8AO5fY6Rg8eyYn&sparams=expire%2Cei%2Cip%2Cid%2Caitags%2Csource%2Crequiressl%2Cgcr%2Cvprv%2Cmime%2Cns%2Cgir%2Cclen%2Cdur%2Clmt&lsparams=mh%2Cmm%2Cmn%2Cms%2Cmv%2Cmvi%2Cpl%2Cinitcwndbps&lsig=AG3C_xAwRgIhAJpmhcFFRSiZb9s8Y0efjo8zARIv9YRmVwIboTBr36BeAiEAyrazqCxL6gW8EDT6sjUxYqwlPpNpaMBThTbaBKoZJXg%3D&sig=AOq0QJ8wRAIgKVBqHeWg7QwOasXcRDOVW4vlRhUpnxQDQagQdHuVPQsCIFJK3EMfEbEmDRKgj-DiNFDokF5AhZFs39raEujVPj8Z", "width": 240, "ext": "mp4", "vcodec": "avc1.4d400c", "acodec": "none", "vbr": 67.402, "downloader_options": {"http_chunk_size": 10485760}, "container": "mp4_dash", "format": "133 - 240x240 (240p)", "protocol": "https", "http_headers": {"User-Agent": "Mozilla/5.0 (Windows NT 10.0; Win64; x64) AppleWebKit/537.36 (KHTML, like Gecko) Chrome/72.0.3626.88 Safari/537.36", "Accept-Charset": "ISO-8859-1,utf-8;q=0.7,*;q=0.7", "Accept": "text/html,application/xhtml+xml,application/xml;q=0.9,*/*;q=0.8", "Accept-Encoding": "gzip, deflate", "Accept-Language": "en-us,en;q=0.5"}}, {"asr": null, "filesize": 791823, "format_id": "134", "format_note": "360p", "fps": 25, "height": 360, "quality": 2, "tbr": 28.627, "url": "https://rr5---sn-0opoxu-ihv6.googlevideo.com/videoplayback?expire=1670742951&ei=Ry-VY6CUEc3tkgac65tQ&ip=189.173.225.87&id=o-AGW8qPrnFC62l8HBPtUaufyw0B3iomcOkIgdfUnlTkgK&itag=134&aitags=133%2C134%2C135%2C136%2C137%2C160%2C242%2C243%2C244%2C247%2C248%2C278&source=youtube&requiressl=yes&mh=4D&mm=31%2C29&mn=sn-0opoxu-ihv6%2Csn-q4flrn7r&ms=au%2Crdu&mv=m&mvi=5&pl=24&gcr=mx&initcwndbps=777500&vprv=1&mime=video%2Fmp4&ns=d-VkRmYy579Rj0Om3oVtrI4J&gir=yes&clen=791823&dur=221.280&lmt=1573727865725340&mt=1670721185&fvip=3&keepalive=yes&fexp=24001373%2C24007246&c=WEB&txp=1311222&n=KrE8AO5fY6Rg8eyYn&sparams=expire%2Cei%2Cip%2Cid%2Caitags%2Csource%2Crequiressl%2Cgcr%2Cvprv%2Cmime%2Cns%2Cgir%2Cclen%2Cdur%2Clmt&lsparams=mh%2Cmm%2Cmn%2Cms%2Cmv%2Cmvi%2Cpl%2Cinitcwndbps&lsig=AG3C_xAwRgIhAOSuA02CoobCzQE852Z1P7b4oznwMvqKJV4_DXpE9lMbAiEAvKq1H0-tK58u2BvDFABo-tdiyTOia7z4KH9mwJS5-Xk%3D&sig=AOq0QJ8wRQIhAKz4A8YLJyyx5GvJKOMl61EVfidUEaOQNtrcG5Pbn8OAAiBboLjglv8SRVutbymLVf_LAHFbT58VPs7y6Iq2LSPxVg==", "width": 360, "ext": "mp4", "vcodec": "avc1.4d4015", "acodec": "none", "vbr": 28.627, "downloader_options": {"http_chunk_size": 10485760}, "container": "mp4_dash", "format": "134 - 360x360 (360p)", "protocol": "https", "http_headers": {"User-Agent": "Mozilla/5.0 (Windows NT 10.0; Win64; x64) AppleWebKit/537.36 (KHTML, like Gecko) Chrome/72.0.3626.88 Safari/537.36", "Accept-Charset": "ISO-8859-1,utf-8;q=0.7,*;q=0.7", "Accept": "text/html,application/xhtml+xml,application/xml;q=0.9,*/*;q=0.8", "Accept-Encoding": "gzip, deflate", "Accept-Language": "en-us,en;q=0.5"}}, {"asr": null, "filesize": 2042456, "format_id": "243", "format_note": "360p", "fps": 25, "height": 360, "quality": 2, "tbr": 73.841, "url": "https://rr5---sn-0opoxu-ihv6.googlevideo.com/videoplayback?expire=1670742951&ei=Ry-VY6CUEc3tkgac65tQ&ip=189.173.225.87&id=o-AGW8qPrnFC62l8HBPtUaufyw0B3iomcOkIgdfUnlTkgK&itag=243&aitags=133%2C134%2C135%2C136%2C137%2C160%2C242%2C243%2C244%2C247%2C248%2C278&source=youtube&requiressl=yes&mh=4D&mm=31%2C29&mn=sn-0opoxu-ihv6%2Csn-q4flrn7r&ms=au%2Crdu&mv=m&mvi=5&pl=24&gcr=mx&initcwndbps=777500&vprv=1&mime=video%2Fwebm&ns=d-VkRmYy579Rj0Om3oVtrI4J&gir=yes&clen=2042456&dur=221.280&lmt=1573728913982568&mt=1670721185&fvip=3&keepalive=yes&fexp=24001373%2C24007246&c=WEB&txp=1301222&n=KrE8AO5fY6Rg8eyYn&sparams=expire%2Cei%2Cip%2Cid%2Caitags%2Csource%2Crequiressl%2Cgcr%2Cvprv%2Cmime%2Cns%2Cgir%2Cclen%2Cdur%2Clmt&lsparams=mh%2Cmm%2Cmn%2Cms%2Cmv%2Cmvi%2Cpl%2Cinitcwndbps&lsig=AG3C_xAwRQIgUHW_1XaVfkcTjU7M9Zo4_Bgff1Tjk1aNOW7Ng5RIvRMCIQDVB0K4_IHgBq5HUPvsoFbnyaEBMRfFlsbDDcSaHy1Y1g%3D%3D&sig=AOq0QJ8wRQIhAIWJFu0YRFdVYrBAOc_VlkPX2lRiyghZY3Co0WU_5DtjAiBWXRwUaSbRrL2inWixyDZa_DESifH95qPc4Di2fxcRMg==", "width": 360, "ext": "webm", "vcodec": "vp9", "acodec": "none", "vbr": 73.841, "downloader_options": {"http_chunk_size": 10485760}, "container": "webm_dash", "format": "243 - 360x360 (360p)", "protocol": "https", "http_headers": {"User-Agent": "Mozilla/5.0 (Windows NT 10.0; Win64; x64) AppleWebKit/537.36 (KHTML, like Gecko) Chrome/72.0.3626.88 Safari/537.36", "Accept-Charset": "ISO-8859-1,utf-8;q=0.7,*;q=0.7", "Accept": "text/html,application/xhtml+xml,application/xml;q=0.9,*/*;q=0.8", "Accept-Encoding": "gzip, deflate", "Accept-Language": "en-us,en;q=0.5"}}, {"asr": null, "filesize": 1528769, "format_id": "135", "format_note": "480p", "fps": 25, "height": 480, "quality": 3, "tbr": 55.27, "url": "https://rr5---sn-0opoxu-ihv6.googlevideo.com/videoplayback?expire=1670742951&ei=Ry-VY6CUEc3tkgac65tQ&ip=189.173.225.87&id=o-AGW8qPrnFC62l8HBPtUaufyw0B3iomcOkIgdfUnlTkgK&itag=135&aitags=133%2C134%2C135%2C136%2C137%2C160%2C242%2C243%2C244%2C247%2C248%2C278&source=youtube&requiressl=yes&mh=4D&mm=31%2C29&mn=sn-0opoxu-ihv6%2Csn-q4flrn7r&ms=au%2Crdu&mv=m&mvi=5&pl=24&gcr=mx&initcwndbps=777500&vprv=1&mime=video%2Fmp4&ns=d-VkRmYy579Rj0Om3oVtrI4J&gir=yes&clen=1528769&dur=221.280&lmt=1573727874445902&mt=1670721185&fvip=3&keepalive=yes&fexp=24001373%2C24007246&c=WEB&txp=1311222&n=KrE8AO5fY6Rg8eyYn&sparams=expire%2Cei%2Cip%2Cid%2Caitags%2Csource%2Crequiressl%2Cgcr%2Cvprv%2Cmime%2Cns%2Cgir%2Cclen%2Cdur%2Clmt&lsparams=mh%2Cmm%2Cmn%2Cms%2Cmv%2Cmvi%2Cpl%2Cinitcwndbps&lsig=AG3C_xAwRQIgI4fNCsj92icGHBjGOVFolgAMkFP4mCyJQVNw-MxyJcsCIQDjxzKKl5rmPeDHqeiOEG-ZBDsVFFCV7mEnyx7-9B4efA%3D%3D&sig=AOq0QJ8wRgIhAKwY8mUt56sYEU7bB3YwmOkxI0LraQmrYNdjPQtOy3QkAiEAqXirHsTS6XponDa4AsHZ1SZ4Dyfy5xlMDgXElr62akI=", "width": 480, "ext": "mp4", "vcodec": "avc1.4d401e", "acodec": "none", "vbr": 55.27, "downloader_options": {"http_chunk_size": 10485760}, "container": "mp4_dash", "format": "135 - 480x480 (480p)", "protocol": "https", "http_headers": {"User-Agent": "Mozilla/5.0 (Windows NT 10.0; Win64; x64) AppleWebKit/537.36 (KHTML, like Gecko) Chrome/72.0.3626.88 Safari/537.36", "Accept-Charset": "ISO-8859-1,utf-8;q=0.7,*;q=0.7", "Accept": "text/html,application/xhtml+xml,application/xml;q=0.9,*/*;q=0.8", "Accept-Encoding": "gzip, deflate", "Accept-Language": "en-us,en;q=0.5"}}, {"asr": null, "filesize": 3598859, "format_id": "244", "format_note": "480p", "fps": 25, "height": 480, "quality": 3, "tbr": 130.11, "url": "https://rr5---sn-0opoxu-ihv6.googlevideo.com/videoplayback?expire=1670742951&ei=Ry-VY6CUEc3tkgac65tQ&ip=189.173.225.87&id=o-AGW8qPrnFC62l8HBPtUaufyw0B3iomcOkIgdfUnlTkgK&itag=244&aitags=133%2C134%2C135%2C136%2C137%2C160%2C242%2C243%2C244%2C247%2C248%2C278&source=youtube&requiressl=yes&mh=4D&mm=31%2C29&mn=sn-0opoxu-ihv6%2Csn-q4flrn7r&ms=au%2Crdu&mv=m&mvi=5&pl=24&gcr=mx&initcwndbps=777500&vprv=1&mime=video%2Fwebm&ns=d-VkRmYy579Rj0Om3oVtrI4J&gir=yes&clen=3598859&dur=221.280&lmt=1573728913985824&mt=1670721185&fvip=3&keepalive=yes&fexp=24001373%2C24007246&c=WEB&txp=1301222&n=KrE8AO5fY6Rg8eyYn&sparams=expire%2Cei%2Cip%2Cid%2Caitags%2Csource%2Crequiressl%2Cgcr%2Cvprv%2Cmime%2Cns%2Cgir%2Cclen%2Cdur%2Clmt&lsparams=mh%2Cmm%2Cmn%2Cms%2Cmv%2Cmvi%2Cpl%2Cinitcwndbps&lsig=AG3C_xAwRQIhANdKy0uLe-DMbx--df2iWXxJf4VIEoigstr85Cr2c9g_AiAk_5mwqm3lrSD0tfWNPrwmY03hLJpW0qonLBI7RGzBmA%3D%3D&sig=AOq0QJ8wRQIgIrbFGjUS3X1ayunhw1-tGbOooMbqywufD6FHWWS-iKICIQDEVhE-6D8MOk4_lmB2F0xi85gWEJtuMPN1yaAIIWJ97A==", "width": 480, "ext": "webm", "vcodec": "vp9", "acodec": "none", "vbr": 130.11, "downloader_options": {"http_chunk_size": 10485760}, "container": "webm_dash", "format": "244 - 480x480 (480p)", "protocol": "https", "http_headers": {"User-Agent": "Mozilla/5.0 (Windows NT 10.0; Win64; x64) AppleWebKit/537.36 (KHTML, like Gecko) Chrome/72.0.3626.88 Safari/537.36", "Accept-Charset": "ISO-8859-1,utf-8;q=0.7,*;q=0.7", "Accept": "text/html,application/xhtml+xml,application/xml;q=0.9,*/*;q=0.8", "Accept-Encoding": "gzip, deflate", "Accept-Language": "en-us,en;q=0.5"}}, {"asr": null, "filesize": 2944178, "format_id": "136", "format_note": "720p", "fps": 25, "height": 720, "quality": 4, "tbr": 106.441, "url": "https://rr5---sn-0opoxu-ihv6.googlevideo.com/videoplayback?expire=1670742951&ei=Ry-VY6CUEc3tkgac65tQ&ip=189.173.225.87&id=o-AGW8qPrnFC62l8HBPtUaufyw0B3iomcOkIgdfUnlTkgK&itag=136&aitags=133%2C134%2C135%2C136%2C137%2C160%2C242%2C243%2C244%2C247%2C248%2C278&source=youtube&requiressl=yes&mh=4D&mm=31%2C29&mn=sn-0opoxu-ihv6%2Csn-q4flrn7r&ms=au%2Crdu&mv=m&mvi=5&pl=24&gcr=mx&initcwndbps=777500&vprv=1&mime=video%2Fmp4&ns=d-VkRmYy579Rj0Om3oVtrI4J&gir=yes&clen=2944178&dur=221.280&lmt=1573727861919241&mt=1670721185&fvip=3&keepalive=yes&fexp=24001373%2C24007246&c=WEB&txp=1311222&n=KrE8AO5fY6Rg8eyYn&sparams=expire%2Cei%2Cip%2Cid%2Caitags%2Csource%2Crequiressl%2Cgcr%2Cvprv%2Cmime%2Cns%2Cgir%2Cclen%2Cdur%2Clmt&lsparams=mh%2Cmm%2Cmn%2Cms%2Cmv%2Cmvi%2Cpl%2Cinitcwndbps&lsig=AG3C_xAwRgIhAPAeld_yH8h1noHwfHOPVzwfLvV_RSNHEr-bO1KqHyB7AiEAxMvbt5e7Uko7zmkXMiBghC1j3_IN46W9aUGtj9KU8lA%3D&sig=AOq0QJ8wRQIgI-3NfG4LAOMOep2JX5BvtQq8sd0hbulZxKsRl_X6bAYCIQDFz4c2nNi0OYsrDwKgSASqEtjwTiv9VYMDkPA01Hy7Gw==", "width": 720, "ext": "mp4", "vcodec": "avc1.4d401f", "acodec": "none", "vbr": 106.441, "downloader_options": {"http_chunk_size": 10485760}, "container": "mp4_dash", "format": "136 - 720x720 (720p)", "protocol": "https", "http_headers": {"User-Agent": "Mozilla/5.0 (Windows NT 10.0; Win64; x64) AppleWebKit/537.36 (KHTML, like Gecko) Chrome/72.0.3626.88 Safari/537.36", "Accept-Charset": "ISO-8859-1,utf-8;q=0.7,*;q=0.7", "Accept": "text/html,application/xhtml+xml,application/xml;q=0.9,*/*;q=0.8", "Accept-Encoding": "gzip, deflate", "Accept-Language": "en-us,en;q=0.5"}}, {"asr": null, "filesize": 7625935, "format_id": "247", "format_note": "720p", "fps": 25, "height": 720, "quality": 4, "tbr": 275.702, "url": "https://rr5---sn-0opoxu-ihv6.googlevideo.com/videoplayback?expire=1670742951&ei=Ry-VY6CUEc3tkgac65tQ&ip=189.173.225.87&id=o-AGW8qPrnFC62l8HBPtUaufyw0B3iomcOkIgdfUnlTkgK&itag=247&aitags=133%2C134%2C135%2C136%2C137%2C160%2C242%2C243%2C244%2C247%2C248%2C278&source=youtube&requiressl=yes&mh=4D&mm=31%2C29&mn=sn-0opoxu-ihv6%2Csn-q4flrn7r&ms=au%2Crdu&mv=m&mvi=5&pl=24&gcr=mx&initcwndbps=777500&vprv=1&mime=video%2Fwebm&ns=d-VkRmYy579Rj0Om3oVtrI4J&gir=yes&clen=7625935&dur=221.280&lmt=1573728914097739&mt=1670721185&fvip=3&keepalive=yes&fexp=24001373%2C24007246&c=WEB&txp=1301222&n=KrE8AO5fY6Rg8eyYn&sparams=expire%2Cei%2Cip%2Cid%2Caitags%2Csource%2Crequiressl%2Cgcr%2Cvprv%2Cmime%2Cns%2Cgir%2Cclen%2Cdur%2Clmt&lsparams=mh%2Cmm%2Cmn%2Cms%2Cmv%2Cmvi%2Cpl%2Cinitcwndbps&lsig=AG3C_xAwRgIhAJWrmvwKTRuyaR2DCsmWYQLR-iDXmHazPCrfpBNPds7mAiEAvLv3NCVxPaL3WRX8TkhtP6Nk67gW_oQalHZwjJ7G_QE%3D&sig=AOq0QJ8wRAIgOL9erbJV1oxvCXHmpUcb2n0Idfucbwff11nU5d_IGt0CIAvVWsTq5xIM3qSpdqVXxVG1Rbsg9sD8KXYbfnK8RCGN", "width": 720, "ext": "webm", "vcodec": "vp9", "acodec": "none", "vbr": 275.702, "downloader_options": {"http_chunk_size": 10485760}, "container": "webm_dash", "format": "247 - 720x720 (720p)", "protocol": "https", "http_headers": {"User-Agent": "Mozilla/5.0 (Windows NT 10.0; Win64; x64) AppleWebKit/537.36 (KHTML, like Gecko) Chrome/72.0.3626.88 Safari/537.36", "Accept-Charset": "ISO-8859-1,utf-8;q=0.7,*;q=0.7", "Accept": "text/html,application/xhtml+xml,application/xml;q=0.9,*/*;q=0.8", "Accept-Encoding": "gzip, deflate", "Accept-Language": "en-us,en;q=0.5"}}, {"asr": null, "filesize": 5250166, "format_id": "137", "format_note": "1080p", "fps": 25, "height": 1080, "quality": 5, "tbr": 189.81, "url": "https://rr5---sn-0opoxu-ihv6.googlevideo.com/videoplayback?expire=1670742951&ei=Ry-VY6CUEc3tkgac65tQ&ip=189.173.225.87&id=o-AGW8qPrnFC62l8HBPtUaufyw0B3iomcOkIgdfUnlTkgK&itag=137&aitags=133%2C134%2C135%2C136%2C137%2C160%2C242%2C243%2C244%2C247%2C248%2C278&source=youtube&requiressl=yes&mh=4D&mm=31%2C29&mn=sn-0opoxu-ihv6%2Csn-q4flrn7r&ms=au%2Crdu&mv=m&mvi=5&pl=24&gcr=mx&initcwndbps=777500&vprv=1&mime=video%2Fmp4&ns=d-VkRmYy579Rj0Om3oVtrI4J&gir=yes&clen=5250166&dur=221.280&lmt=1573727865023880&mt=1670721185&fvip=3&keepalive=yes&fexp=24001373%2C24007246&c=WEB&txp=1311222&n=KrE8AO5fY6Rg8eyYn&sparams=expire%2Cei%2Cip%2Cid%2Caitags%2Csource%2Crequiressl%2Cgcr%2Cvprv%2Cmime%2Cns%2Cgir%2Cclen%2Cdur%2Clmt&lsparams=mh%2Cmm%2Cmn%2Cms%2Cmv%2Cmvi%2Cpl%2Cinitcwndbps&lsig=AG3C_xAwRQIgBDzlTMMlzsE1pPTnyAdyarhvJxUrJYmbMW5tIYxmDxcCIQDRVCKmHOjvHqdhnoIecv5qeXmkDFyxYyL0UkQVOvqQ6A%3D%3D&sig=AOq0QJ8wRQIhAJAFELt-9uL70kll8SaiQkcY8FaPagg45J4KImEViz35AiAi5mcb6QeftRrzKQeCiD4ZM6jVBM6Egse0J_x8H6U4iA==", "width": 1080, "ext": "mp4", "vcodec": "avc1.640020", "acodec": "none", "vbr": 189.81, "downloader_options": {"http_chunk_size": 10485760}, "container": "mp4_dash", "format": "137 - 1080x1080 (1080p)", "protocol": "https", "http_headers": {"User-Agent": "Mozilla/5.0 (Windows NT 10.0; Win64; x64) AppleWebKit/537.36 (KHTML, like Gecko) Chrome/72.0.3626.88 Safari/537.36", "Accept-Charset": "ISO-8859-1,utf-8;q=0.7,*;q=0.7", "Accept": "text/html,application/xhtml+xml,application/xml;q=0.9,*/*;q=0.8", "Accept-Encoding": "gzip, deflate", "Accept-Language": "en-us,en;q=0.5"}}, {"asr": null, "filesize": 14158861, "format_id": "248", "format_note": "1080p", "fps": 25, "height": 1080, "quality": 5, "tbr": 511.889, "url": "https://rr5---sn-0opoxu-ihv6.googlevideo.com/videoplayback?expire=1670742951&ei=Ry-VY6CUEc3tkgac65tQ&ip=189.173.225.87&id=o-AGW8qPrnFC62l8HBPtUaufyw0B3iomcOkIgdfUnlTkgK&itag=248&aitags=133%2C134%2C135%2C136%2C137%2C160%2C242%2C243%2C244%2C247%2C248%2C278&source=youtube&requiressl=yes&mh=4D&mm=31%2C29&mn=sn-0opoxu-ihv6%2Csn-q4flrn7r&ms=au%2Crdu&mv=m&mvi=5&pl=24&gcr=mx&initcwndbps=777500&vprv=1&mime=video%2Fwebm&ns=d-VkRmYy579Rj0Om3oVtrI4J&gir=yes&clen=14158861&dur=221.280&lmt=1573728694271646&mt=1670721185&fvip=3&keepalive=yes&fexp=24001373%2C24007246&c=WEB&txp=1301222&n=KrE8AO5fY6Rg8eyYn&sparams=expire%2Cei%2Cip%2Cid%2Caitags%2Csource%2Crequiressl%2Cgcr%2Cvprv%2Cmime%2Cns%2Cgir%2Cclen%2Cdur%2Clmt&lsparams=mh%2Cmm%2Cmn%2Cms%2Cmv%2Cmvi%2Cpl%2Cinitcwndbps&lsig=AG3C_xAwRAIgAaNnEFc9woywoOnYXR3DEGMzU00vDKf5xU4RXUX6RHUCIGcgGUbTh9SJvKDO5JJtWcdgkOyFG5YGUEggUP7ZILQb&sig=AOq0QJ8wRQIgaH0M0sL_462HcDpEwvfOSNMOo7dIqpJmNaHwg4EI5T0CIQDdGKjgfFmJJ4Pm8z24VZySuix-E3lBboAUTUSL8RjpSQ==", "width": 1080, "ext": "webm", "vcodec": "vp9", "acodec": "none", "vbr": 511.889, "downloader_options": {"http_chunk_size": 10485760}, "container": "webm_dash", "format": "248 - 1080x1080 (1080p)", "protocol": "https", "http_headers": {"User-Agent": "Mozilla/5.0 (Windows NT 10.0; Win64; x64) AppleWebKit/537.36 (KHTML, like Gecko) Chrome/72.0.3626.88 Safari/537.36", "Accept-Charset": "ISO-8859-1,utf-8;q=0.7,*;q=0.7", "Accept": "text/html,application/xhtml+xml,application/xml;q=0.9,*/*;q=0.8", "Accept-Encoding": "gzip, deflate", "Accept-Language": "en-us,en;q=0.5"}}, {"asr": 44100, "filesize": null, "format_id": "18", "format_note": "360p", "fps": 25, "height": 360, "quality": 2, "tbr": 157.531, "url": "https://rr5---sn-0opoxu-ihv6.googlevideo.com/videoplayback?expire=1670742951&ei=Ry-VY6CUEc3tkgac65tQ&ip=189.173.225.87&id=o-AGW8qPrnFC62l8HBPtUaufyw0B3iomcOkIgdfUnlTkgK&itag=18&source=youtube&requiressl=yes&mh=4D&mm=31%2C29&mn=sn-0opoxu-ihv6%2Csn-q4flrn7r&ms=au%2Crdu&mv=m&mvi=5&pl=24&gcr=mx&initcwndbps=777500&vprv=1&mime=video%2Fmp4&ns=kgFmvGNTJerq9CmmFtkvezcJ&cnr=14&ratebypass=yes&dur=221.332&lmt=1661277054049317&mt=1670721185&fvip=3&fexp=24001373%2C24007246&c=WEB&txp=1318224&n=Zvjee3X64rdAzeNOb&sparams=expire%2Cei%2Cip%2Cid%2Citag%2Csource%2Crequiressl%2Cgcr%2Cvprv%2Cmime%2Cns%2Ccnr%2Cratebypass%2Cdur%2Clmt&lsparams=mh%2Cmm%2Cmn%2Cms%2Cmv%2Cmvi%2Cpl%2Cinitcwndbps&lsig=AG3C_xAwRQIhAIM_eQlkF2AguGLHwxJTTRSTcjU080sxjlVZ2Gmcg3MhAiBODs-OiSqNJ0djYTNrNwynpU4vW_FCTClAZ385csZTag%3D%3D&sig=AOq0QJ8wRgIhANgwB_yrX4xhezw_oNT8NticxEVFSYItN0fxYeEzcdxlAiEA9MV0m5AfNuKdSboj4_ysa13gaaJaYYk1hghxlszF9UA=", "width": 360, "ext": "mp4", "vcodec": "avc1.42001E", "acodec": "mp4a.40.2", "format": "18 - 360x360 (360p)", "protocol": "https", "http_headers": {"User-Agent": "Mozilla/5.0 (Windows NT 10.0; Win64; x64) AppleWebKit/537.36 (KHTML, like Gecko) Chrome/72.0.3626.88 Safari/537.36", "Accept-Charset": "ISO-8859-1,utf-8;q=0.7,*;q=0.7", "Accept": "text/html,application/xhtml+xml,application/xml;q=0.9,*/*;q=0.8", "Accept-Encoding": "gzip, deflate", "Accept-Language": "en-us,en;q=0.5"}}], "thumbnails": [{"height": 94, "url": "https://i.ytimg.com/vi/pbGAy8GzWaI/hqdefault.jpg?sqp=-oaymwEbCKgBEF5IVfKriqkDDggBFQAAiEIYAXABwAEG&rs=AOn4CLAHbMLl4u5ItXwmJDdzdLqgIy8-GA", "width": 168, "resolution": "168x94", "id": "0"}, {"height": 110, "url": "https://i.ytimg.com/vi/pbGAy8GzWaI/hqdefault.jpg?sqp=-oaymwEbCMQBEG5IVfKriqkDDggBFQAAiEIYAXABwAEG&rs=AOn4CLCLC0Q7Ue5RQTXwpyGDq5BW5qJXhg", "width": 196, "resolution": "196x110", "id": "1"}, {"height": 138, "url": "https://i.ytimg.com/vi/pbGAy8GzWaI/hqdefault.jpg?sqp=-oaymwEcCPYBEIoBSFXyq4qpAw4IARUAAIhCGAFwAcABBg==&rs=AOn4CLC_VRRv_zWQO0BzT_UZdc2REKanrg", "width": 246, "resolution": "246x138", "id": "2"}, {"height": 188, "url": "https://i.ytimg.com/vi/pbGAy8GzWaI/hqdefault.jpg?sqp=-oaymwEcCNACELwBSFXyq4qpAw4IARUAAIhCGAFwAcABBg==&rs=AOn4CLC3pZZzdCLAOVO_i4VRpTAHIELk6A", "width": 336, "resolution": "336x188", "id": "3"}], "description": "Provided to YouTube by JVCKENWOOD Victor Entertainment Corp.\n\n\u30a4\u30d6\u30cb\u30f3\u30b0\u3000\u30b7\u30e3\u30ef\u30fc \u00b7 La Fee de la Goutte\n\nMizu no Ongaku\n\n\u2117 JVCKENWOOD Victor Entertainment\n\nReleased on: 1989-07-05\n\nAuto-generated by YouTube.", "upload_date": "20180709", "uploader": "Jun-Ichi Kamiyama - Topic", "uploader_id": "UCjFNbgfyzCrS8XuSuc1dljA", "uploader_url": "http://www.youtube.com/channel/UCjFNbgfyzCrS8XuSuc1dljA", "channel_id": "UCjFNbgfyzCrS8XuSuc1dljA", "channel_url": "https://www.youtube.com/channel/UCjFNbgfyzCrS8XuSuc1dljA", "duration": 221, "view_count": 2604, "average_rating": null, "age_limit": 0, "webpage_url": "https://www.youtube.com/watch?v=pbGAy8GzWaI", "categories": ["Music"], "tags": ["La Fee de la Goutte", "\u795e\u5c71\u7d14\u4e00", "\u30ab\u30df\u30e4\u30de\u30b8\u30e6\u30f3\u30a4\u30c1", "Mizu no Ongaku", "\u6c34\u306e\u97f3\u697d", "\u30a4\u30d6\u30cb\u30f3\u30b0", "\u30b7\u30e3\u30ef\u30fc", "Evening Shower", "\u30a4\u30d6\u30cb\u30f3\u30b0\u30b7\u30e4\u30ef\u30fc"], "is_live": null, "album": "Mizu no Ongaku", "artist": "La Fee de la Goutte", "track": "\u30a4\u30d6\u30cb\u30f3\u30b0\u3000\u30b7\u30e3\u30ef\u30fc", "release_date": "19890705", "release_year": 1989, "channel": "Jun-Ichi Kamiyama - Topic", "creator": "La Fee de la Goutte", "alt_title": "\u30a4\u30d6\u30cb\u30f3\u30b0\u3000\u30b7\u30e3\u30ef\u30fc", "extractor": "youtube", "webpage_url_basename": "watch", "extractor_key": "Youtube", "playlist": null, "playlist_index": null, "thumbnail": "https://i.ytimg.com/vi/pbGAy8GzWaI/hqdefault.jpg?sqp=-oaymwEcCNACELwBSFXyq4qpAw4IARUAAIhCGAFwAcABBg==&rs=AOn4CLC3pZZzdCLAOVO_i4VRpTAHIELk6A", "display_id": "pbGAy8GzWaI", "asr": 44100, "filesize": null, "format_id": "18", "format_note": "360p", "fps": 25, "height": 360, "quality": 2, "tbr": 157.531, "url": "https://rr5---sn-0opoxu-ihv6.googlevideo.com/videoplayback?expire=1670742951&ei=Ry-VY6CUEc3tkgac65tQ&ip=189.173.225.87&id=o-AGW8qPrnFC62l8HBPtUaufyw0B3iomcOkIgdfUnlTkgK&itag=18&source=youtube&requiressl=yes&mh=4D&mm=31%2C29&mn=sn-0opoxu-ihv6%2Csn-q4flrn7r&ms=au%2Crdu&mv=m&mvi=5&pl=24&gcr=mx&initcwndbps=777500&vprv=1&mime=video%2Fmp4&ns=kgFmvGNTJerq9CmmFtkvezcJ&cnr=14&ratebypass=yes&dur=221.332&lmt=1661277054049317&mt=1670721185&fvip=3&fexp=24001373%2C24007246&c=WEB&txp=1318224&n=Zvjee3X64rdAzeNOb&sparams=expire%2Cei%2Cip%2Cid%2Citag%2Csource%2Crequiressl%2Cgcr%2Cvprv%2Cmime%2Cns%2Ccnr%2Cratebypass%2Cdur%2Clmt&lsparams=mh%2Cmm%2Cmn%2Cms%2Cmv%2Cmvi%2Cpl%2Cinitcwndbps&lsig=AG3C_xAwRQIhAIM_eQlkF2AguGLHwxJTTRSTcjU080sxjlVZ2Gmcg3MhAiBODs-OiSqNJ0djYTNrNwynpU4vW_FCTClAZ385csZTag%3D%3D&sig=AOq0QJ8wRgIhANgwB_yrX4xhezw_oNT8NticxEVFSYItN0fxYeEzcdxlAiEA9MV0m5AfNuKdSboj4_ysa13gaaJaYYk1hghxlszF9UA=", "width": 360, "ext": "mp4", "vcodec": "avc1.42001E", "acodec": "mp4a.40.2", "format": "18 - 360x360 (360p)", "protocol": "https", "http_headers": {"User-Agent": "Mozilla/5.0 (Windows NT 10.0; Win64; x64) AppleWebKit/537.36 (KHTML, like Gecko) Chrome/72.0.3626.88 Safari/537.36", "Accept-Charset": "ISO-8859-1,utf-8;q=0.7,*;q=0.7", "Accept": "text/html,application/xhtml+xml,application/xml;q=0.9,*/*;q=0.8", "Accept-Encoding": "gzip, deflate", "Accept-Language": "en-us,en;q=0.5"}, "fulltitle": "\u30a4\u30d6\u30cb\u30f3\u30b0\u3000\u30b7\u30e3\u30ef\u30fc", "_filename": "\u30a4\u30d6\u30cb\u30f3\u30b0\u3000\u30b7\u30e3\u30ef\u30fc-pbGAy8GzWaI.mp4"}